setup.py
setup_newgame.py
fis3/__init__.py
fis3/fis.py
fis3/resource.py
fis3.egg-info/PKG-INFO
fis3.egg-info/SOURCES.txt
fis3.egg-info/dependency_links.txt
fis3.egg-info/requires.txt
fis3.egg-info/top_level.txt
fis3/extensions/__init__.py
fis3/extensions/framework.py
fis3/extensions/load.py
fis3/extensions/placeholder.py
fis3/extensions/script.py
fis3/extensions/style.py
fis3/extensions/uri.py