Metadata-Version: 1.0
Name: fis3
Version: 0.0.8
Summary: 扩展flask,支持fis3
Home-page: https://github.com/fancyboynet/pip-fis
Author: Fancy
Author-email: fancyboynet@gmail.com
License: MIT Licence
Keywords: pip,fis,fis3
Platform: any
